v8py.cpython-35m-darwin.so
v8py-0.9.10.dist-info/DESCRIPTION.rst
v8py-0.9.10.dist-info/METADATA
v8py-0.9.10.dist-info/RECORD
v8py-0.9.10.dist-info/WHEEL
v8py-0.9.10.dist-info/metadata.json
v8py-0.9.10.dist-info/top_level.txt
