Metadata-Version: 2.0
Name: v8py
Version: 0.9.10
Summary: Write Python APIs, then call them from JavaScript using the V8 engine.
Home-page: https://github.com/tbodt/v8py
Author: Theodore Dubois
Author-email: tblodt@icloud.com
License: LGPLv3
Keywords: v8,javascript
Platform: UNKNOWN
Classifier: Development Status :: 3 - Alpha
Classifier: License :: OSI Approved :: GNU Lesser General Public License v3 or later (LGPLv3+)
Classifier: Topic :: Software Development :: Interpreters
Classifier: Programming Language :: Python :: 2.7
Classifier: Programming Language :: Python :: 3.5
